chips/or_chip.v

module or_chip(out, a, b);
	input a, b;
	output out;

	wire w1, w2;
	
	nand(w1, a, a);
	nand(w2, b, b);
	nand(out, w1, w2);
endmodule

chips/and_chip.v

module and_chip(out, a, b);
	input a, b;
	output out;
	
	wire w1;
	nand(w1, a, b);
	nand(out, w1, w1);
	
endmodule

chips/not_chip.v

module not_chip(out, a);
	input a;
	output out;
	
	nand(out, a, a);
	
endmodule

chips/mux_chip_2to1.v
module mux_chip_2to1(out, a, b, s);
	input a, b, s;
	output out;	

	wire w1, w2, w3;
	not_chip not_chip(w1, s);	
	and_chip and_chip1(w2, a, w1);
	and_chip and_chip2(w3, b, s);				
	or_chip or_chip(out, w2, w3);
	
endmodule

chips/tests/mux_2to1_test.v
module dut;
	reg a, b, s;
	wire out;
	
	mux_chip_2to1 mux(out, a, b, s);
	//$display("a b c out");
	initial begin
		$dumpfile("mux.vcd");
		$dumpvars(0, dut);
		a = 0; b = 0; s = 0; #10
		$display("%b %b %b %b", a, b, s, out);
		a = 1; b = 0; s = 0; #10
		$display("%b %b %b %b", a, b, s, out);
		a = 0; b = 1; s = 0; #10
		$display("%b %b %b %b", a, b, s, out);
		a = 1; b = 1; s = 0; #10
		$display("%b %b %b %b", a, b, s, out);
		a = 0; b = 0; s = 1; #10
		$display("%b %b %b %b", a, b, s, out);
		a = 1; b = 0; s = 1; #10
		$display("%b %b %b %b", a, b, s, out);
		a = 0; b = 1; s = 1; #10
		$display("%b %b %b %b", a, b, s, out);
		a = 1; b = 1; s = 1; #10
		$display("%b %b %b %b", a, b, s, out);
		$finish;
	end
			
		
endmodule

chips/mux.vcd
$date
	Fri Jun  2 18:43:56 2023
$end
$version
	Icarus Verilog
$end
$timescale
	1s
$end
$scope module dut $end
$var wire 1 ! out $end
$var reg 1 " a $end
$var reg 1 # b $end
$var reg 1 $ s $end
$scope module mux $end
$var wire 1 " a $end
$var wire 1 # b $end
$var wire 1 $ s $end
$var wire 1 % w3 $end
$var wire 1 & w2 $end
$var wire 1 ' w1 $end
$var wire 1 ! out $end
$scope module and_chip1 $end
$var wire 1 " a $end
$var wire 1 & out $end
$var wire 1 ( w1 $end
$var wire 1 ' b $end
$upscope $end
$scope module and_chip2 $end
$var wire 1 # a $end
$var wire 1 $ b $end
$var wire 1 % out $end
$var wire 1 ) w1 $end
$upscope $end
$scope module not_chip $end
$var wire 1 $ a $end
$var wire 1 ' out $end
$upscope $end
$scope module or_chip $end
$var wire 1 & a $end
$var wire 1 % b $end
$var wire 1 ! out $end
$var wire 1 * w1 $end
$var wire 1 + w2 $end
$upscope $end
$upscope $end
$upscope $end
$enddefinitions $end
$comment Show the parameter values. $end
$dumpall
$end
#0
$dumpvars
1+
1*
1)
1(
1'
0&
0%
0$
0#
0"
0!
$end
#10
1!
0*
1&
0(
1"
#20
0!
1*
0&
1(
1#
0"
#30
1!
0*
1&
0(
1"
#40
0!
1*
0&
0'
1(
1$
0#
0"
#50
1"
#60
1!
0+
1%
0)
1#
0"
#70
1"
